CHANGES.txt
COPYING.txt
MANIFEST.in
README.rst
config.ini.example
setup.cfg
setup.py
magnatune/__init__.py
magnatune/api.py
magnatune/config.py
magnatune/main.py
magnatune/search.py
magnatune.egg-info/PKG-INFO
magnatune.egg-info/SOURCES.txt
magnatune.egg-info/dependency_links.txt
magnatune.egg-info/entry_points.txt
magnatune.egg-info/requires.txt
magnatune.egg-info/top_level.txt
magnatune/tests/__init__.py
magnatune/tests/test_api.py
magnatune/tests/test_search.py