Metadata-Version: 1.0
Name: magnatune
Version: 0.2
Summary: Command line utility and lib to interact with the music website magnatune
Home-page: https://github.com/madjar/python-magnatune
Author: Georges Dubus
Author-email: georges.dubus@compiletoi.net
License: GPLv3
Keywords: magnatune music stream
Platform: UNKNOWN
Classifier: Programming Language :: Python
Classifier: Programming Language :: Python :: 3
Classifier: Development Status :: 4 - Beta
Classifier: Environment :: Console
Classifier: Intended Audience :: Developers
Classifier: Intended Audience :: End Users/Desktop
Classifier: License :: OSI Approved :: GNU General Public License (GPL)
Classifier: Operating System :: OS Independent
Classifier: Topic :: Software Development :: Libraries :: Python Modules
Classifier: Topic :: Multimedia
